[{"message":"","timestamp":"2025-09-01T20:45:26.588318595Z"},{"message":"\u001b[35m[Region: europe-west4]\u001b[0m","timestamp":"2025-09-01T20:45:29.203674066Z"},{"message":"\u001b[35m=========================","timestamp":"2025-09-01T20:45:29.204370040Z"},{"message":"Using Detected Dockerfile","timestamp":"2025-09-01T20:45:29.204406130Z"},{"message":"=========================","timestamp":"2025-09-01T20:45:29.204416428Z"},{"message":"\u001b[0m","timestamp":"2025-09-01T20:45:29.204422576Z"},{"message":"context: 2ccc-TMbb","timestamp":"2025-09-01T20:45:29.204444712Z"},{"message":"[internal] load build definition from Dockerfile","timestamp":"2025-09-01T20:45:29.333054456Z"},{"message":"[internal] load build definition from Dockerfile","timestamp":"2025-09-01T20:45:29.333561069Z"},{"message":"[internal] load build definition from Dockerfile","timestamp":"2025-09-01T20:45:29.333883380Z"},{"message":"[internal] load build definition from Dockerfile","timestamp":"2025-09-01T20:45:29.345648444Z"},{"message":"[internal] load metadata for docker.io/library/node:20-alpine","timestamp":"2025-09-01T20:45:29.347922702Z"},{"message":"[auth] library/node:pull token for registry-1.docker.io","timestamp":"2025-09-01T20:45:29.449642543Z"},{"message":"[auth] library/node:pull token for registry-1.docker.io","timestamp":"2025-09-01T20:45:29.449711168Z"},{"message":"[internal] load metadata for docker.io/library/node:20-alpine","timestamp":"2025-09-01T20:45:30.373899613Z"},{"message":"[internal] load .dockerignore","timestamp":"2025-09-01T20:45:30.374274993Z"},{"message":"[internal] load .dockerignore","timestamp":"2025-09-01T20:45:30.374329080Z"},{"message":"[internal] load .dockerignore","timestamp":"2025-09-01T20:45:30.374426890Z"},{"message":"[internal] load .dockerignore","timestamp":"2025-09-01T20:45:30.385492462Z"},{"message":"[stage-1 4/4] WORKDIR /app","timestamp":"2025-09-01T20:45:30.390296154Z"},{"message":"[stage-1 3/4] COPY --from=build /app/dist /app","timestamp":"2025-09-01T20:45:30.390346668Z"},{"message":"[build 6/6] RUN npm run build:deploy","timestamp":"2025-09-01T20:45:30.390355233Z"},{"message":"[build 5/6] COPY . .","timestamp":"2025-09-01T20:45:30.390364976Z"},{"message":"[build 4/6] RUN npm ci","timestamp":"2025-09-01T20:45:30.390374746Z"},{"message":"[build 3/6] COPY package*.json ./","timestamp":"2025-09-01T20:45:30.390381839Z"},{"message":"[internal] load build context","timestamp":"2025-09-01T20:45:30.390388166Z"},{"message":"[build 2/6] WORKDIR /app","timestamp":"2025-09-01T20:45:30.390394405Z"},{"message":"[stage-1 2/4] RUN npm install -g serve","timestamp":"2025-09-01T20:45:30.390400404Z"},{"message":"[build 1/6] FROM docker.io/library/node:20-alpine@sha256:df02558528d3d3d0d621f112e232611aecfee7cbc654f6b375765f72bb262799","timestamp":"2025-09-01T20:45:30.390408444Z"},{"message":"[build 1/6] FROM docker.io/library/node:20-alpine@sha256:df02558528d3d3d0d621f112e232611aecfee7cbc654f6b375765f72bb262799","timestamp":"2025-09-01T20:45:30.390423555Z"},{"message":"[internal] load build context","timestamp":"2025-09-01T20:45:30.390433597Z"},{"message":"[build 1/6] FROM docker.io/library/node:20-alpine@sha256:df02558528d3d3d0d621f112e232611aecfee7cbc654f6b375765f72bb262799","timestamp":"2025-09-01T20:45:30.398364918Z"},{"message":"[build 1/6] FROM docker.io/library/node:20-alpine@sha256:df02558528d3d3d0d621f112e232611aecfee7cbc654f6b375765f72bb262799","timestamp":"2025-09-01T20:45:30.398430818Z"},{"message":"[internal] load build context","timestamp":"2025-09-01T20:45:30.398503453Z"},{"message":"[build 1/6] FROM docker.io/library/node:20-alpine@sha256:df02558528d3d3d0d621f112e232611aecfee7cbc654f6b375765f72bb262799","timestamp":"2025-09-01T20:45:30.398558222Z"},{"message":"[build 1/6] FROM docker.io/library/node:20-alpine@sha256:df02558528d3d3d0d621f112e232611aecfee7cbc654f6b375765f72bb262799","timestamp":"2025-09-01T20:45:30.431737803Z"},{"message":"[build 1/6] FROM docker.io/library/node:20-alpine@sha256:df02558528d3d3d0d621f112e232611aecfee7cbc654f6b375765f72bb262799","timestamp":"2025-09-01T20:45:30.434032183Z"},{"message":"[internal] load build context","timestamp":"2025-09-01T20:45:30.452851739Z"},{"message":"[build 1/6] FROM docker.io/library/node:20-alpine@sha256:df02558528d3d3d0d621f112e232611aecfee7cbc654f6b375765f72bb262799","timestamp":"2025-09-01T20:45:30.862248007Z"},{"message":"[stage-1 2/4] RUN npm install -g serve","timestamp":"2025-09-01T20:45:31.937354769Z"},{"message":"[build 2/6] WORKDIR /app","timestamp":"2025-09-01T20:45:31.937400969Z"},{"message":"[build 2/6] WORKDIR /app","timestamp":"2025-09-01T20:45:32.153807464Z"},{"message":"[build 3/6] COPY package*.json ./","timestamp":"2025-09-01T20:45:32.155132327Z"},{"message":"[build 3/6] COPY package*.json ./","timestamp":"2025-09-01T20:45:32.179269103Z"},{"message":"[build 4/6] RUN npm ci","timestamp":"2025-09-01T20:45:32.180691601Z"},{"message":"\nadded 88 packages in 3s\n","timestamp":"2025-09-01T20:45:34.806690134Z"},{"message":"\n","timestamp":"2025-09-01T20:45:34.806797359Z"},{"message":"24 packages are looking for funding\n  run `npm fund` for details\n","timestamp":"2025-09-01T20:45:34.806816594Z"},{"message":"npm notice\nnpm notice New major version of npm available! 10.8.2 -> 11.5.2\nnpm notice Changelog: https://github.com/npm/cli/releases/tag/v11.5.2\nnpm notice To update run: npm install -g npm@11.5.2\nnpm notice\n","timestamp":"2025-09-01T20:45:34.809050754Z"},{"message":"[stage-1 2/4] RUN npm install -g serve","timestamp":"2025-09-01T20:45:34.971339489Z"},{"message":"\nadded 544 packages, and audited 545 packages in 7s\n","timestamp":"2025-09-01T20:45:39.388670361Z"},{"message":"\n214 packages are looking for funding\n  run `npm fund` for details\n","timestamp":"2025-09-01T20:45:39.388688986Z"},{"message":"\nfound 0 vulnerabilities\n","timestamp":"2025-09-01T20:45:39.390192214Z"},{"message":"npm notice\nnpm notice New major version of npm available! 10.8.2 -> 11.5.2\nnpm notice Changelog: https://github.com/npm/cli/releases/tag/v11.5.2\nnpm notice To update run: npm install -g npm@11.5.2\nnpm notice\n","timestamp":"2025-09-01T20:45:39.391651078Z"},{"message":"[build 4/6] RUN npm ci","timestamp":"2025-09-01T20:45:39.639932050Z"},{"message":"[build 5/6] COPY . .","timestamp":"2025-09-01T20:45:39.640739738Z"},{"message":"[build 5/6] COPY . .","timestamp":"2025-09-01T20:45:39.802175998Z"},{"message":"[build 6/6] RUN npm run build:deploy","timestamp":"2025-09-01T20:45:39.804114045Z"},{"message":"\n> promtok_frontend@0.0.0 build:deploy\n> vite build\n\n","timestamp":"2025-09-01T20:45:40.032425255Z"},{"message":"vite v7.1.4 building for production...\n","timestamp":"2025-09-01T20:45:40.30459861Z"},{"message":"transforming...\n","timestamp":"2025-09-01T20:45:40.634013581Z"},{"message":"✓ 1075 modules transformed.\n","timestamp":"2025-09-01T20:45:43.686056468Z"},{"message":"✗ Build failed in 3.10s\n","timestamp":"2025-09-01T20:45:43.691911353Z"},{"message":"error during build:\n[vite:load-fallback] Could not load /app/src/lib/utils (imported by src/components/ui/card.tsx): ENOENT: no such file or directory, open '/app/src/lib/utils'\n    at async open (node:internal/fs/promises:639:25)\n    at async Object.readFile (node:internal/fs/promises:1246:14)\n    at async Object.handler (file:///app/node_modules/vite/dist/node/chunks/dep-C6pp_iVS.js:33964:21)\n    at async PluginDriver.hookFirstAndGetPlugin (file:///app/node_modules/rollup/dist/es/shared/node-entry.js:22277:28)\n    at async file:///app/node_modules/rollup/dist/es/shared/node-entry.js:21277:33\n    at async Queue.work (file:///app/node_modules/rollup/dist/es/shared/node-entry.js:22505:32)\n","timestamp":"2025-09-01T20:45:43.69197723Z"},{"message":"[build 6/6] RUN npm run build:deploy","timestamp":"2025-09-01T20:45:43.945131511Z"},{"message":"Dockerfile:25","timestamp":"2025-09-01T20:45:43.965454954Z"},{"message":"-------------------","timestamp":"2025-09-01T20:45:43.965517952Z"},{"message":"23 |     # Build the application (Vite will inline VITE_* values if provided)","timestamp":"2025-09-01T20:45:43.965525928Z"},{"message":"24 |     # Use a deploy build that skips tsc to avoid type-check failures during container builds","timestamp":"2025-09-01T20:45:43.965532907Z"},{"message":"25 | >>> RUN npm run build:deploy","timestamp":"2025-09-01T20:45:43.965541070Z"},{"message":"26 |","timestamp":"2025-09-01T20:45:43.965546775Z"},{"message":"27 |     # Production stage with simple static server","timestamp":"2025-09-01T20:45:43.965556477Z"},{"message":"-------------------","timestamp":"2025-09-01T20:45:43.965561341Z"},{"message":"ERROR: failed to build: failed to solve: process \"/bin/sh -c npm run build:deploy\" did not complete successfully: exit code: 1","timestamp":"2025-09-01T20:45:43.965566903Z"}]